RAINLotus/__init__.py
RAINLotus/__main__.py
RAINLotus/p.py
RAINLotus/prism.min.css
RAINLotus/r.py
RAINLotus/rainink.min.css
RAINLotus/t.py
RAINLotus/v.py
RAINLotus-1.99.0.dist-info/LICENSE
RAINLotus-1.99.0.dist-info/METADATA
RAINLotus-1.99.0.dist-info/WHEEL
RAINLotus-1.99.0.dist-info/top_level.txt
RAINLotus-1.99.0.dist-info/RECORD
