Metadata-Version: 2.1
Name: RAINLotus
Version: 1.99.0
Summary: A -tranquilac- lightweight markup language with nearly 40 syntaxes.
Home-page: https://github.com/20x48/RAINLotus
Author: 20x48
Author-email: the20x48@outlook.com
License: UNKNOWN
Project-URL: Github, https://github.com/20x48/RAINLotus
Platform: UNKNOWN
Classifier: License :: OSI Approved :: MIT License
Classifier: Operating System :: OS Independent
Classifier: Programming Language :: Python :: 3
Classifier: Programming Language :: Python :: 3.6
Classifier: Programming Language :: Python :: 3.7
Classifier: Programming Language :: Python :: 3.8
Classifier: Programming Language :: Python :: 3.9
Classifier: Topic :: Utilities
Classifier: Topic :: Documentation
Classifier: Topic :: Text Processing :: Markup :: HTML
Classifier: Topic :: Software Development :: Documentation
Classifier: Topic :: Software Development :: Libraries :: Python Modules
Requires-Python: >=3.6
